[{"id":"corkeryuaabyfc","date":"2018-05-02T13:20:17.354Z","mediaFilename":"corkeryuaabyfc.png","caption":"â™« DOO DOO DOO DOO! â™ª (corker)","postedToGit":true,"htmlFragment":"<li class=\"pane\">\n  <div class=\"time-stamp entry-meta\">\n    <a href=\"corkeryuaabyfc.html\">\n      <time datetime=\"2018-05-02T13:20:17.354Z\">2018-5-2 09:20:17</time>\n    </a>\n  </div><img src=\"media/corkeryuaabyfc.png\" alt=\"â™« DOO DOO DOO DOO! â™ª (corker)\"></video><div class=\"media-caption entry-meta\">\n      <a href=\"corkeryuaabyfc.html\">â™« DOO DOO DOO DOO! â™ª (corker)</a></div></li>","postedSingleVideoPage":true},{"id":"aggravationTKuFuvXx","date":"2018-05-02T16:20:06.758Z","mediaFilename":"aggravationTKuFuvXx.png","caption":"â™« DOO DOO DOO DOO! â™ª (aggravation)","postedToGit":true,"htmlFragment":"<li class=\"pane\">\n  <div class=\"time-stamp entry-meta\">\n    <a href=\"aggravationTKuFuvXx.html\">\n      <time datetime=\"2018-05-02T16:20:06.758Z\">2018-5-2 12:20:06</time>\n    </a>\n  </div><img src=\"media/aggravationTKuFuvXx.png\" alt=\"â™« DOO DOO DOO DOO! â™ª (aggravation)\"></video><div class=\"media-caption entry-meta\">\n      <a href=\"aggravationTKuFuvXx.html\">â™« DOO DOO DOO DOO! â™ª (aggravation)</a></div></li>","postedSingleVideoPage":true},{"id":"DaoistamuIKPMK","date":"2018-05-02T19:20:07.708Z","mediaFilename":"DaoistamuIKPMK.png","caption":"ğ„ DOO DOO DOO DOO! â™© (Daoist)","postedToGit":true,"htmlFragment":"<li class=\"pane\">\n  <div class=\"time-stamp entry-meta\">\n    <a href=\"DaoistamuIKPMK.html\">\n      <time datetime=\"2018-05-02T19:20:07.708Z\">2018-5-2 15:20:07</time>\n    </a>\n  </div><img src=\"media/DaoistamuIKPMK.png\" alt=\"ğ„ DOO DOO DOO DOO! â™© (Daoist)\"></video><div class=\"media-caption entry-meta\">\n      <a href=\"DaoistamuIKPMK.html\">ğ„ DOO DOO DOO DOO! â™© (Daoist)</a></div></li>","postedSingleVideoPage":true}]