[{"id":"ArminianismIumMVptJ","date":"2018-10-07T04:20:06.200Z","mediaFilename":"ArminianismIumMVptJ.png","caption":"♬ DOO DOO DOO DOO! ♪ (Arminianism)","postedToGit":true,"htmlFragment":"<li class=\"pane\">\n  <div class=\"time-stamp entry-meta\">\n    <a href=\"ArminianismIumMVptJ.html\">\n      <time datetime=\"2018-10-07T04:20:06.200Z\">2018-10-7 00:20:06</time>\n    </a>\n  </div><img src=\"media/ArminianismIumMVptJ.png\" alt=\"♬ DOO DOO DOO DOO! ♪ (Arminianism)\"></video><div class=\"media-caption entry-meta\">\n      <a href=\"ArminianismIumMVptJ.html\">♬ DOO DOO DOO DOO! ♪ (Arminianism)</a></div></li>","postedSingleVideoPage":true},{"id":"brookekkhUnaut","date":"2018-10-07T07:20:07.916Z","mediaFilename":"brookekkhUnaut.png","caption":"♪ DOO DOO DOO DOO! ♪ (brooke)","postedToGit":true,"htmlFragment":"<li class=\"pane\">\n  <div class=\"time-stamp entry-meta\">\n    <a href=\"brookekkhUnaut.html\">\n      <time datetime=\"2018-10-07T07:20:07.916Z\">2018-10-7 03:20:07</time>\n    </a>\n  </div><img src=\"media/brookekkhUnaut.png\" alt=\"♪ DOO DOO DOO DOO! ♪ (brooke)\"></video><div class=\"media-caption entry-meta\">\n      <a href=\"brookekkhUnaut.html\">♪ DOO DOO DOO DOO! ♪ (brooke)</a></div></li>","postedSingleVideoPage":true}]